ChangeLog
MANIFEST.in
README.txt
commandlineapp.py
pavement.py
paver-minilib.zip
setup.py
test_commandlineapp.py
CommandLineApp.egg-info/PKG-INFO
CommandLineApp.egg-info/SOURCES.txt
CommandLineApp.egg-info/dependency_links.txt
CommandLineApp.egg-info/not-zip-safe
CommandLineApp.egg-info/top_level.txt
docs/build/html/commandlineapp.html
docs/build/html/genindex.html
docs/build/html/history.html
docs/build/html/index.html
docs/build/html/py-modindex.html
docs/build/html/search.html
docs/build/html/searchindex.js
docs/build/html/PyMagArticle/index.html
docs/build/html/_sources/commandlineapp.txt
docs/build/html/_sources/history.txt
docs/build/html/_sources/index.txt
docs/build/html/_sources/PyMagArticle/index.txt
docs/build/html/_static/basic.css
docs/build/html/_static/doctools.js
docs/build/html/_static/file.png
docs/build/html/_static/jquery.js
docs/build/html/_static/minus.png
docs/build/html/_static/nature.css
docs/build/html/_static/plus.png
docs/build/html/_static/pygments.css
docs/build/html/_static/searchtools.js
docs/build/html/_static/underscore.js
docs/source/commandlineapp.rst
docs/source/conf.py
docs/source/history.rst
docs/source/index.rst
docs/source/PyMagArticle/Listing1.txt
docs/source/PyMagArticle/Listing2.py
docs/source/PyMagArticle/Listing3.py
docs/source/PyMagArticle/Listing4.py
docs/source/PyMagArticle/Listing5.py
docs/source/PyMagArticle/Listing6.py
docs/source/PyMagArticle/Listing7.py
docs/source/PyMagArticle/Listing8.py
docs/source/PyMagArticle/callouts.txt
docs/source/PyMagArticle/index.rst