Metadata-Version: 1.1
Name: CommandLineApp
Version: 3.0.7
Summary: Base class for command line applications
Home-page: http://www.doughellmann.com/projects/CommandLineApp/
Author: Doug Hellmann
Author-email: doug.hellmann@gmail.com
License: UNKNOWN
Download-URL: http://www.doughellmann.com/downloads/CommandLineApp-3.0.7.tar.gz
Platform: Any
Classifier: Development Status :: 5 - Production/Stable
Classifier: License :: OSI Approved :: BSD License
Classifier: Programming Language :: Python
Classifier: Intended Audience :: Developers
Classifier: Environment :: Console
Provides: commandlineapp
